Metadata-Version: 2.1
Name: MijnSimpel
Version: 0.6
Summary: Python Client to Mijn Simpel
Home-page: https://github.com/aleksandr-vin/mijn-simpel-python-client
Author: Aleksandr Vinokurov
Author-email: aleksandr.vin@gmail.com
License: MIT
Download-URL: https://github.com/aleksandr-vin/mijn-simpel-python-client/archive/v0.5.tar.gz
Keywords: scraping,mijn-simpel,telecom,usage,cli,client,simpel,nl
Platform: UNKNOWN
Classifier: Development Status :: 3 - Alpha
Classifier: Environment :: Console
Classifier: Intended Audience :: Developers
Classifier: Intended Audience :: Customer Service
Classifier: Intended Audience :: End Users/Desktop
Classifier: Intended Audience :: Information Technology
Classifier: Intended Audience :: Telecommunications Industry
Classifier: Topic :: Software Development
Classifier: Topic :: Communications :: Telephony
Classifier: Topic :: Home Automation
Classifier: Topic :: Internet
Classifier: Topic :: Scientific/Engineering :: Information Analysis
Classifier: Topic :: Software Development :: Libraries
Classifier: Topic :: Software Development :: Libraries :: Python Modules
Classifier: Topic :: Software Development :: User Interfaces
Classifier: Topic :: System :: Monitoring
Classifier: Natural Language :: Dutch
Classifier: Natural Language :: English
Classifier: License :: OSI Approved :: MIT License
Classifier: Programming Language :: Python :: 3
